{
  "book": "Mazmur",
  "chapter": 82,
  "verses": [
    {
      "verse": 1,
      "text": "Tingting tu angka panguhum mandabu uhum na sintong 1-8",
      "type": "title"
    },
    {
      "verse": 1,
      "text": "Ende sian si Asap. Tindang do Debata di bagasan luhutan ni Debata, mandabu uhum do Ibana di tongatonga ni angka panguhum.",
      "type": "content"
    },
    {
      "verse": 2,
      "text": "Sadia leleng on do pageduhonmuna uhum, jala dingkan an muna angka parjahat i? Sela!",
      "type": "content"
    },
    {
      "verse": 3,
      "text": "Patingkos hamu ma uhum tu na metmet dohot tu na sopot so marama, ondihon hamu ma na dangol dohot na pogos.",
      "type": "content"
    },
    {
      "verse": 4,
      "text": "Palua hamu ma na metmet dohot na pogos, sian tangan ni angka parjahat ma palua hamu nasida.",
      "type": "content"
    },
    {
      "verse": 5,
      "text": "Ndang mananda nasida, jala ndang olo nasida parrohaon, sai mardalani di haholomon do nasida, jadi reberebe ma sude angka ojahan ni tano on.",
      "type": "content"
    },
    {
      "verse": 6,
      "text": "Ianggo ahu, nunga pola hudok nian: Angka Debata do hamu, jala anak ni Natumimbul do hamu sudena.",
      "type": "content"
    },
    {
      "verse": 7,
      "text": "Alai atik pe songon i mate do hamu songon jolma hian, jala tinggang do hamu sogot songon raja na asing sada.",
      "type": "content"
    },
    {
      "verse": 8,
      "text": "Hehe ma Ho, ale Debata, sai uhum ma tano on, ai guru di Ho hian do angka parbegu sudena!",
      "type": "content"
    }
  ]
}